<?xml version="1.0" encoding="utf-8"?>
<ArrayOfAvaliacao xmlns:xsd="http://www.w3.org/2001/XMLSchema" xmlns:xsi="http://www.w3.org/2001/XMLSchema-instance">
  <Avaliacao>
    <Id>1</Id>
    <Nota>5</Nota>
    <cliente>
      <Id>1</Id>
      <Nome>Alcides</Nome>
      <Telefone>84 98787878</Telefone>
      <Endereço>Rua Jardins, Nº666</Endereço>
      <Nascimento>2000-04-23T00:00:00</Nascimento>
    </cliente>
    <clienteId>1</clienteId>
  </Avaliacao>
  <Avaliacao>
    <Id>2</Id>
    <Nota>4</Nota>
    <cliente>
      <Id>2</Id>
      <Nome>Israel</Nome>
      <Telefone>84 987515555</Telefone>
      <Endereço>Rua bandeira, 244c</Endereço>
      <Nascimento>1999-11-18T00:00:00</Nascimento>
    </cliente>
    <clienteId>2</clienteId>
  </Avaliacao>
</ArrayOfAvaliacao>